Metadata-Version: 2.1
Name: smart-dist
Version: 1.0.2
Summary: Binomial and Gaussian distributions along with a Crypto Analytic Tool
Home-page: https://github.com/invest41/smart-dist
Author: Alao David I.
Author-email: alaodavid41@gmail.com
License: MIT
Platform: UNKNOWN
